aimcore/__init__.py
aimcore/error_handling.py
aimcore/callbacks/__init__.py
aimcore/callbacks/caller.py
aimcore/callbacks/events.py
aimcore/callbacks/helpers.py
aimcore/cleanup/__init__.py
aimcore/cli/__init__.py
aimcore/cli/cli.py
aimcore/cli/utils.py
aimcore/cli/watcher_cli.py
aimcore/cli/conatiners/__init__.py
aimcore/cli/conatiners/commands.py
aimcore/cli/conatiners/utils.py
aimcore/cli/convert/__init__.py
aimcore/cli/convert/commands.py
aimcore/cli/convert/processors/__init__.py
aimcore/cli/convert/processors/mlflow.py
aimcore/cli/convert/processors/tensorboard.py
aimcore/cli/convert/processors/wandb.py
aimcore/cli/init/__init__.py
aimcore/cli/init/commands.py
aimcore/cli/migrate/__init__.py
aimcore/cli/migrate/commands.py
aimcore/cli/migrate/utils.py
aimcore/cli/package/__init__.py
aimcore/cli/package/commands.py
aimcore/cli/package/utils.py
aimcore/cli/package/watcher.py
aimcore/cli/server/__init__.py
aimcore/cli/server/commands.py
aimcore/cli/storage/__init__.py
aimcore/cli/storage/commands.py
aimcore/cli/telemetry/__init__.py
aimcore/cli/telemetry/commands.py
aimcore/cli/ui/__init__.py
aimcore/cli/ui/commands.py
aimcore/cli/ui/utils.py
aimcore/cli/version/__init__.py
aimcore/cli/version/commands.py
aimcore/reporter/__init__.py
aimcore/transport/__init__.py
aimcore/transport/client.py
aimcore/transport/config.py
aimcore/transport/handlers.py
aimcore/transport/heartbeat.py
aimcore/transport/message_utils.py
aimcore/transport/remote_resource.py
aimcore/transport/router.py
aimcore/transport/rpc_queue.py
aimcore/transport/server.py
aimcore/transport/tracking.py
aimcore/web/__init__.py
aimcore/web/configs.py
aimcore/web/run.py
aimcore/web/utils.py
aimcore/web/api/__init__.py
aimcore/web/api/db.py
aimcore/web/api/utils.py
aimcore/web/api/views.py
aimcore/web/api/boards/__init__.py
aimcore/web/api/boards/models.py
aimcore/web/api/boards/pydantic_models.py
aimcore/web/api/boards/views.py
aimcore/web/api/dashboard_apps/__init__.py
aimos-1.0.0.dist-info/LICENSE
aimos-1.0.0.dist-info/METADATA
aimos-1.0.0.dist-info/WHEEL
aimos-1.0.0.dist-info/entry_points.txt
aimos-1.0.0.dist-info/top_level.txt
aimos-1.0.0.dist-info/RECORD
